{
  "experience": [
    {
      "time": "2021 - 2023",
      "name": "Nubi",
      "position": "Sr Software Engineer",
      "description": "Lorem ipsum dolor sit amet, consectetur adipiscing elit. Quisque scelerisque diam non nisi semper, et elementum lorem ornare. Maecenas placerat facilisis mollis. Duis sagittis ligula in sodales vehicula.",
      "techs": [
        "React-Native",
        "ReactJS",
        "NodeJS",
        "ExpressJS",
        "Jest",
        "Docker",
        "WebView Components",
        "Firebase"
      ]
    },
    {
      "time": "2020 - 2021",
      "name": "Swiss Medical",
      "position": "Fullstack Developer",
      "description": "Lorem ipsum dolor sit amet, consectetur adipiscing elit. Quisque scelerisque diam non nisi semper, et elementum lorem ornare. Maecenas placerat facilisis mollis. Duis sagittis ligula in sodales vehicula.",
      "techs": [
        "ReactJS",
        "NodeJS",
        "ExpressJS",
        "NextJS",
        "MongoDB",
        "Docker",
        "Styled-Components"
      ]
    },
    {
      "time": "2017 - 2020",
      "name": "Jaits",
      "position": "Fullstack Developer",
      "description": "App para viajes",
      "techs": [
        "React-Native",
        "ReactJS",
        "Expo IO",
        "NodeJS",
        "MongoDB",
        "Docker",
        "Material-UI",
        "Redux",
        "Socket IO"
      ]
    },
    {
      "time": "2016 - 2017",
      "name": "JMA Asociados",
      "position": "Developer",
      "description": "Management system"
    }
  ],
  "education": [
    {
      "time": "2013 - 2017",
      "name": "UNLa",
      "position": "Lic. en Sistemas",
      "description": "Lorem ipsum dolor sit amet, consectetur adipiscing elit. Quisque scelerisque diam non nisi semper, et elementum lorem ornare. Maecenas placerat facilisis mollis. Duis sagittis ligula in sodales vehicula."
    }
  ],
  "portfolio": [
    {
      "title": "App Landing Page",
      "img": "/assets/portfolio-example.webp",
      "created": "",
      "techs": [
        "Javascript",
        "ReactJS v18",
        "React-Native v0.64"
      ],
      "description": "Est consectetur veniam mollit minim duis ad quis deserunt animcat esse adipisicing veniam commodo sint officia cillum ex. Nisi ullamco pariatur adipisicing laborum in minim ullamco officia sint sunt est. Nulla eiusmod consectetur dolore dolor culpa labore quis incididunt. Quis velit laborum mollit qui ut irure irure ipsum velit labore. Fugiat aliqua ut tempor ullamco proident nostrud sint ad aute.",
      "repo": null
    },
    {
      "title": "Title 2",
      "img": "/assets/portfolio-example.webp"
    },
    {
      "title": "Title 3",
      "img": "/assets/portfolio-example.webp"
    },
    {
      "title": "Title 4",
      "img": "/assets/portfolio-example.webp"
    },
    {
      "title": "Title 5",
      "img": "/assets/portfolio-example.webp"
    },
    {
      "title": "Title 6",
      "img": "/assets/portfolio-example.webp"
    }
  ]
}